{
    "tokens": [
        "In",
        "Washington",
        "today",
        ",",
        "the",
        "Federal",
        "Aviation",
        "Administration",
        "released",
        "air",
        "traffic",
        "control",
        "tapes",
        "from",
        "the",
        "night",
        "the",
        "TWA",
        "Flight",
        "eight",
        "hundred",
        "went",
        "down.",
        "There's",
        "nothing",
        "new",
        "on",
        "why",
        "the",
        "plane",
        "exploded",
        ",",
        "but",
        "you",
        "cannot",
        "miss",
        "the",
        "moment.",
        "ABC's",
        "Lisa",
        "Stark",
        "has",
        "more.",
        "There",
        "was",
        "no",
        "hint",
        "of",
        "trouble",
        "in",
        "the",
        "last",
        "conversation",
        "between",
        "controllers",
        "and",
        "TWA",
        "pilot",
        "Steven",
        "Snyder",
        "TWA",
        "eight",
        "hundred",
        "climb",
        "maintain",
        "one",
        "five",
        "thousand.",
        "TWA's",
        "eight",
        "hundred",
        "heavy",
        "climb",
        "and",
        "maintain",
        "one",
        "five",
        "thousand",
        "leavin-",
        "three",
        "thousand.",
        "But",
        "a",
        "minute",
        "and",
        "a",
        "half",
        "later,",
        "a",
        "pilot",
        "from",
        "a",
        "nearby",
        "flight",
        "calls",
        "in.",
        "Ah,",
        "we",
        "just",
        "saw",
        "an",
        "explosion",
        "up",
        "ahead",
        "of",
        "us",
        "here",
        "about",
        "sixteen",
        "thousand",
        "feet",
        "or",
        "something",
        "like",
        "that.",
        "It",
        "just",
        "went",
        "down.",
        "The",
        "controller",
        "at",
        "Boston",
        "center",
        "tries",
        "to",
        "raise",
        "TWA",
        "eight",
        "hundred.",
        "TWA",
        "eight",
        "hundred,",
        "if",
        "you",
        "hear",
        "center,",
        "ident",
        ".",
        "There",
        "is",
        "no",
        "response",
        ".",
        "Later,",
        "the",
        "controller",
        "asks",
        "the",
        "Eastwind",
        "pilot",
        "for",
        "more",
        "details.",
        "Ah",
        "yes,",
        "sir.",
        "It-",
        "It",
        "just",
        "blew",
        "up",
        "in",
        "the",
        "air,",
        "and",
        "then",
        "we",
        "saw",
        "two",
        "fireballs",
        "go",
        "down",
        "to",
        "the,",
        "to",
        "the",
        "water,",
        "and",
        "there",
        "was",
        "a",
        "big",
        "small,",
        "ah,",
        "smoke,",
        "from",
        "ah,",
        "coming",
        "up",
        "from",
        "that.",
        "At",
        "one",
        "point,",
        "when",
        "it",
        "became",
        "clear",
        "controllers",
        "could",
        "not",
        "contact",
        "the",
        "plane,",
        "someone",
        "said",
        "a",
        "prayer.",
        "TWA",
        "eight",
        "hundred",
        "center,",
        "I",
        "think",
        "that",
        "was",
        "him.",
        "I",
        "think",
        "so.",
        "God",
        "bless",
        "him.",
        "Lisa",
        "Stark",
        "ABC",
        "news",
        "Washington"
    ],
    "allMentions": [
        {
            "eventIndex": -1,
            "axisType": "main",
            "rootAxisEventId": -1,
            "corefState": "unknown",
            "m_id": "269",
            "tokens": "blew",
            "tokens_ids": [
                160
            ],
            "event_class": "OCCURRENCE"
        },
        {
            "eventIndex": -1,
            "axisType": "main",
            "rootAxisEventId": -1,
            "corefState": "unknown",
            "m_id": "259",
            "tokens": "calls",
            "tokens_ids": [
                94
            ],
            "event_class": "REPORTING"
        },
        {
            "eventIndex": -1,
            "axisType": "main",
            "rootAxisEventId": -1,
            "corefState": "unknown",
            "m_id": "270",
            "tokens": "saw",
            "tokens_ids": [
                168
            ],
            "event_class": "PERCEPTION"
        },
        {
            "eventIndex": -1,
            "axisType": "main",
            "rootAxisEventId": -1,
            "corefState": "unknown",
            "m_id": "260",
            "tokens": "saw",
            "tokens_ids": [
                99
            ],
            "event_class": "PERCEPTION"
        },
        {
            "eventIndex": -1,
            "axisType": "main",
            "rootAxisEventId": -1,
            "corefState": "unknown",
            "m_id": "271",
            "tokens": "go",
            "tokens_ids": [
                171
            ],
            "event_class": "OCCURRENCE"
        },
        {
            "eventIndex": -1,
            "axisType": "main",
            "rootAxisEventId": -1,
            "corefState": "unknown",
            "m_id": "272",
            "tokens": "coming",
            "tokens_ids": [
                188
            ],
            "event_class": "OCCURRENCE"
        },
        {
            "eventIndex": -1,
            "axisType": "main",
            "rootAxisEventId": -1,
            "corefState": "unknown",
            "m_id": "262",
            "tokens": "went",
            "tokens_ids": [
                117
            ],
            "event_class": "OCCURRENCE"
        },
        {
            "eventIndex": -1,
            "axisType": "main",
            "rootAxisEventId": -1,
            "corefState": "unknown",
            "m_id": "273",
            "tokens": "became",
            "tokens_ids": [
                197
            ],
            "event_class": "I_STATE"
        },
        {
            "eventIndex": -1,
            "axisType": "main",
            "rootAxisEventId": -1,
            "corefState": "unknown",
            "m_id": "276",
            "tokens": "said",
            "tokens_ids": [
                206
            ],
            "event_class": "OCCURRENCE"
        },
        {
            "eventIndex": -1,
            "axisType": "main",
            "rootAxisEventId": -1,
            "corefState": "unknown",
            "m_id": "253",
            "tokens": "went",
            "tokens_ids": [
                21
            ],
            "event_class": "OCCURRENCE"
        },
        {
            "eventIndex": -1,
            "axisType": "main",
            "rootAxisEventId": -1,
            "corefState": "unknown",
            "m_id": "254",
            "tokens": "exploded",
            "tokens_ids": [
                30
            ],
            "event_class": "OCCURRENCE"
        },
        {
            "eventIndex": -1,
            "axisType": "main",
            "rootAxisEventId": -1,
            "corefState": "unknown",
            "m_id": "252",
            "tokens": "released",
            "tokens_ids": [
                8
            ],
            "event_class": "OCCURRENCE"
        }
    ],
    "allPairs": [
        {
            "firstEventText": "saw",
            "secondEventText": "said",
            "_firstId": "270",
            "_secondId": "276",
            "_relation": "BEFORE"
        },
        {
            "firstEventText": "released",
            "secondEventText": "went",
            "_firstId": "252",
            "_secondId": "253",
            "_relation": "AFTER"
        },
        {
            "firstEventText": "released",
            "secondEventText": "exploded",
            "_firstId": "252",
            "_secondId": "254",
            "_relation": "AFTER"
        },
        {
            "firstEventText": "went",
            "secondEventText": "exploded",
            "_firstId": "253",
            "_secondId": "254",
            "_relation": "VAGUE"
        },
        {
            "firstEventText": "calls",
            "secondEventText": "saw",
            "_firstId": "259",
            "_secondId": "260",
            "_relation": "EQUAL"
        },
        {
            "firstEventText": "saw",
            "secondEventText": "went",
            "_firstId": "260",
            "_secondId": "262",
            "_relation": "AFTER"
        },
        {
            "firstEventText": "blew",
            "secondEventText": "saw",
            "_firstId": "269",
            "_secondId": "270",
            "_relation": "BEFORE"
        },
        {
            "firstEventText": "blew",
            "secondEventText": "go",
            "_firstId": "269",
            "_secondId": "271",
            "_relation": "BEFORE"
        },
        {
            "firstEventText": "blew",
            "secondEventText": "coming",
            "_firstId": "269",
            "_secondId": "272",
            "_relation": "BEFORE"
        },
        {
            "firstEventText": "saw",
            "secondEventText": "go",
            "_firstId": "270",
            "_secondId": "271",
            "_relation": "VAGUE"
        },
        {
            "firstEventText": "saw",
            "secondEventText": "coming",
            "_firstId": "270",
            "_secondId": "272",
            "_relation": "VAGUE"
        },
        {
            "firstEventText": "go",
            "secondEventText": "coming",
            "_firstId": "271",
            "_secondId": "272",
            "_relation": "BEFORE"
        },
        {
            "firstEventText": "blew",
            "secondEventText": "became",
            "_firstId": "269",
            "_secondId": "273",
            "_relation": "BEFORE"
        },
        {
            "firstEventText": "blew",
            "secondEventText": "said",
            "_firstId": "269",
            "_secondId": "276",
            "_relation": "BEFORE"
        },
        {
            "firstEventText": "saw",
            "secondEventText": "became",
            "_firstId": "270",
            "_secondId": "273",
            "_relation": "VAGUE"
        },
        {
            "firstEventText": "go",
            "secondEventText": "became",
            "_firstId": "271",
            "_secondId": "273",
            "_relation": "BEFORE"
        },
        {
            "firstEventText": "go",
            "secondEventText": "said",
            "_firstId": "271",
            "_secondId": "276",
            "_relation": "BEFORE"
        },
        {
            "firstEventText": "coming",
            "secondEventText": "became",
            "_firstId": "272",
            "_secondId": "273",
            "_relation": "BEFORE"
        },
        {
            "firstEventText": "coming",
            "secondEventText": "said",
            "_firstId": "272",
            "_secondId": "276",
            "_relation": "BEFORE"
        },
        {
            "firstEventText": "became",
            "secondEventText": "said",
            "_firstId": "273",
            "_secondId": "276",
            "_relation": "BEFORE"
        }
    ]
}