{
    "tokens": [
        "A",
        "group",
        "of",
        "investors",
        "led",
        "by",
        "Giant",
        "Group",
        "Ltd.",
        "and",
        "its",
        "chairman,",
        "Burt",
        "Sugarman,",
        "said",
        "it",
        "filed",
        "with",
        "federal",
        "antitrust",
        "regulators",
        "for",
        "clearance",
        "to",
        "buy",
        "more",
        "than",
        "50%",
        "of",
        "the",
        "stock",
        "of",
        "Rally's",
        "Inc.,",
        "a",
        "fast-food",
        "company",
        "based",
        "in",
        "Louisville,",
        "Ky.",
        "Rally's",
        "operates",
        "and",
        "franchises",
        "about",
        "160",
        "fast-food",
        "restaurants",
        "throughout",
        "the",
        "U.S.",
        "The",
        "company",
        "went",
        "public",
        "earlier",
        "this",
        "month",
        ",",
        "offering",
        "1,745,000",
        "shares",
        "of",
        "common",
        "stock",
        "at",
        "$15",
        "a",
        "share.",
        "Giant",
        "has",
        "interests",
        "in",
        "cement",
        "making",
        "and",
        "newsprint.",
        "The",
        "investor",
        "group",
        "includes",
        "Restaurant",
        "Investment",
        "Partnership,",
        "a",
        "California",
        "general",
        "partnership,",
        "and",
        "three",
        "Rally's",
        "directors:",
        "Mr.",
        "Sugarman,",
        "James",
        "M.",
        "Trotter",
        "III",
        "and",
        "William",
        "E.",
        "Trotter",
        "II.",
        "The",
        "group",
        "currently",
        "holds",
        "3,027,330",
        "Rally's",
        "shares,",
        "or",
        "45.2%",
        "of",
        "its",
        "commmon",
        "shares",
        "outstanding.",
        "Giant",
        "Group",
        "owned",
        "22%",
        "of",
        "Rally's",
        "shares",
        "before",
        "the",
        "initial",
        "public",
        "offering",
        ".",
        "A",
        "second",
        "group",
        "of",
        "three",
        "company",
        "directors,",
        "aligned",
        "with",
        "Rally's",
        "founder",
        "James",
        "Patterson,",
        "also",
        "is",
        "seeking",
        "control",
        "of",
        "the",
        "fast-food",
        "chain.",
        "It",
        "is",
        "estimated",
        "that",
        "the",
        "Patterson",
        "group",
        "controls",
        "more",
        "than",
        "40%",
        "of",
        "Rally's",
        "stock.",
        "Rally",
        "officials",
        "weren't",
        "available",
        "to",
        "comment",
        "late",
        "yesterday",
        ".",
        "For",
        "the",
        "year",
        "ended",
        "July",
        "2",
        ",",
        "Rally",
        "had",
        "net",
        "income",
        "of",
        "$2.4",
        "million,",
        "or",
        "34",
        "cents",
        "a",
        "share,",
        "on",
        "revenue",
        "of",
        "$52.9",
        "million."
    ],
    "allMentions": [
        {
            "eventIndex": -1,
            "axisType": "main",
            "rootAxisEventId": -1,
            "corefState": "unknown",
            "m_id": "156",
            "tokens": "owned",
            "tokens_ids": [
                120
            ],
            "event_class": "STATE"
        },
        {
            "eventIndex": -1,
            "axisType": "main",
            "rootAxisEventId": -1,
            "corefState": "unknown",
            "m_id": "160",
            "tokens": "controls",
            "tokens_ids": [
                159
            ],
            "event_class": "STATE"
        },
        {
            "eventIndex": -1,
            "axisType": "main",
            "rootAxisEventId": -1,
            "corefState": "unknown",
            "m_id": "158",
            "tokens": "seeking",
            "tokens_ids": [
                146
            ],
            "event_class": "I_ACTION"
        },
        {
            "eventIndex": -1,
            "axisType": "main",
            "rootAxisEventId": -1,
            "corefState": "unknown",
            "m_id": "155",
            "tokens": "offering",
            "tokens_ids": [
                60
            ],
            "event_class": "OCCURRENCE"
        },
        {
            "eventIndex": -1,
            "axisType": "main",
            "rootAxisEventId": -1,
            "corefState": "unknown",
            "m_id": "154",
            "tokens": "went",
            "tokens_ids": [
                54
            ],
            "event_class": "OCCURRENCE"
        },
        {
            "eventIndex": -1,
            "axisType": "main",
            "rootAxisEventId": -1,
            "corefState": "unknown",
            "m_id": "151",
            "tokens": "filed",
            "tokens_ids": [
                16
            ],
            "event_class": "I_ACTION"
        },
        {
            "eventIndex": -1,
            "axisType": "main",
            "rootAxisEventId": -1,
            "corefState": "unknown",
            "m_id": "150",
            "tokens": "said",
            "tokens_ids": [
                14
            ],
            "event_class": "REPORTING"
        }
    ],
    "allPairs": [
        {
            "firstEventText": "said",
            "secondEventText": "filed",
            "_firstId": "150",
            "_secondId": "151",
            "_relation": "AFTER"
        },
        {
            "firstEventText": "said",
            "secondEventText": "went",
            "_firstId": "150",
            "_secondId": "154",
            "_relation": "AFTER"
        },
        {
            "firstEventText": "said",
            "secondEventText": "offering",
            "_firstId": "150",
            "_secondId": "155",
            "_relation": "AFTER"
        },
        {
            "firstEventText": "filed",
            "secondEventText": "went",
            "_firstId": "151",
            "_secondId": "154",
            "_relation": "AFTER"
        },
        {
            "firstEventText": "filed",
            "secondEventText": "offering",
            "_firstId": "151",
            "_secondId": "155",
            "_relation": "AFTER"
        },
        {
            "firstEventText": "went",
            "secondEventText": "offering",
            "_firstId": "154",
            "_secondId": "155",
            "_relation": "BEFORE"
        },
        {
            "firstEventText": "owned",
            "secondEventText": "seeking",
            "_firstId": "156",
            "_secondId": "158",
            "_relation": "BEFORE"
        },
        {
            "firstEventText": "seeking",
            "secondEventText": "controls",
            "_firstId": "158",
            "_secondId": "160",
            "_relation": "AFTER"
        }
    ]
}